README.md
async_ready.py
setup.py
async_ready.egg-info/PKG-INFO
async_ready.egg-info/SOURCES.txt
async_ready.egg-info/dependency_links.txt
async_ready.egg-info/top_level.txt